<?xml version="1.0" encoding="UTF-8"?>

<livre>

 <tableau>
  <molecule> Keflex (cephalexin)</molecule>
  <ancrem><![CDATA[<a href="./Rx03C.html#Cephalexin">Keflex (cephalexin)</a>]]></ancrem>
  <indication> </indication>
  <ancrei> </ancrei>
  <grossesse1> </grossesse1>
  <grossesse2> </grossesse2>
  <grossesse3> </grossesse3>
  <grossesse4> </grossesse4>
  <grossesse5> </grossesse5>
  <grossesse6> </grossesse6>
  <grossesse7> </grossesse7>
  <grossesse8> </grossesse8>
  <grossesse9> </grossesse9>
  <recommandationgrossesse> </recommandationgrossesse>
  <allaitement1> </allaitement1>
  <allaitement2> </allaitement2>
  <allaitement3> </allaitement3>
  <allaitement4> </allaitement4>
  <allaitement5> </allaitement5>
  <allaitement6> </allaitement6>
  <allaitement7> </allaitement7>
  <allaitement8> </allaitement8>
  <allaitement9> </allaitement9>
  <recommandationallaitement> </recommandationallaitement>
 </tableau>

 <tableau>
  <molecule> Ketek (telithromycin)</molecule>
  <ancrem><![CDATA[<a href="./Rx20T.html#Telithromycin">Ketek (telithromycin)</a>]]></ancrem>
  <indication> </indication>
  <ancrei> </ancrei>
  <grossesse1> </grossesse1>
  <grossesse2> </grossesse2>
  <grossesse3> </grossesse3>
  <grossesse4> </grossesse4>
  <grossesse5> </grossesse5>
  <grossesse6> </grossesse6>
  <grossesse7> </grossesse7>
  <grossesse8> </grossesse8>
  <grossesse9> </grossesse9>
  <recommandationgrossesse> </recommandationgrossesse>
  <allaitement1> </allaitement1>
  <allaitement2> </allaitement2>
  <allaitement3> </allaitement3>
  <allaitement4> </allaitement4>
  <allaitement5> </allaitement5>
  <allaitement6> </allaitement6>
  <allaitement7> </allaitement7>
  <allaitement8> </allaitement8>
  <allaitement9> </allaitement9>
  <recommandationallaitement> </recommandationallaitement>
  </tableau>

</livre>